teerace_tml-0.3.data/data/tml/mapres/bg_cloud1.png
teerace_tml-0.3.data/data/tml/mapres/bg_cloud2.png
teerace_tml-0.3.data/data/tml/mapres/bg_cloud3.png
teerace_tml-0.3.data/data/tml/mapres/desert_doodads.png
teerace_tml-0.3.data/data/tml/mapres/desert_main.png
teerace_tml-0.3.data/data/tml/mapres/desert_mountains.png
teerace_tml-0.3.data/data/tml/mapres/desert_mountains2.png
teerace_tml-0.3.data/data/tml/mapres/desert_sun.png
teerace_tml-0.3.data/data/tml/mapres/generic_deathtiles.png
teerace_tml-0.3.data/data/tml/mapres/generic_unhookable.png
teerace_tml-0.3.data/data/tml/mapres/grass_doodads.png
teerace_tml-0.3.data/data/tml/mapres/grass_main.png
teerace_tml-0.3.data/data/tml/mapres/jungle_background.png
teerace_tml-0.3.data/data/tml/mapres/jungle_deathtiles.png
teerace_tml-0.3.data/data/tml/mapres/jungle_doodads.png
teerace_tml-0.3.data/data/tml/mapres/jungle_main.png
teerace_tml-0.3.data/data/tml/mapres/jungle_midground.png
teerace_tml-0.3.data/data/tml/mapres/jungle_unhookables.png
teerace_tml-0.3.data/data/tml/mapres/moon.png
teerace_tml-0.3.data/data/tml/mapres/mountains.png
teerace_tml-0.3.data/data/tml/mapres/snow.png
teerace_tml-0.3.data/data/tml/mapres/stars.png
teerace_tml-0.3.data/data/tml/mapres/sun.png
teerace_tml-0.3.data/data/tml/mapres/winter_doodads.png
teerace_tml-0.3.data/data/tml/mapres/winter_main.png
teerace_tml-0.3.data/data/tml/mapres/winter_mountains.png
teerace_tml-0.3.data/data/tml/mapres/winter_mountains2.png
teerace_tml-0.3.data/data/tml/mapres/winter_mountains3.png
teerace_tml-0.3.data/data/tml/maps/ctf1.map
teerace_tml-0.3.data/data/tml/maps/ctf2.map
teerace_tml-0.3.data/data/tml/maps/ctf3.map
teerace_tml-0.3.data/data/tml/maps/ctf4.map
teerace_tml-0.3.data/data/tml/maps/ctf5.map
teerace_tml-0.3.data/data/tml/maps/ctf6.map
teerace_tml-0.3.data/data/tml/maps/ctf7.map
teerace_tml-0.3.data/data/tml/maps/dm1.map
teerace_tml-0.3.data/data/tml/maps/dm2.map
teerace_tml-0.3.data/data/tml/maps/dm6.map
teerace_tml-0.3.dist-info/METADATA
teerace_tml-0.3.dist-info/RECORD
teerace_tml-0.3.dist-info/WHEEL
teerace_tml-0.3.dist-info/top_level.txt
