Metadata-Version: 2.1
Name: teerace-tml
Version: 0.3
Summary: tml      :copyright: 2010-2011 by the TML Team, see AUTHORS for more details.     :license: GNU GPL, see LICENSE for more details.
Home-page: UNKNOWN
Author: TML Team
Author-email: UNKNOWN
License: UNKNOWN
Platform: UNKNOWN
Classifier: Programming Language :: Python :: 3
Classifier: License :: OSI Approved :: GNU General Public License (GPL)
Requires-Dist: pypng (>=0.0.12)
